Metadata-Version: 2.1
Name: termfunk
Version: 0.3.0
Summary: A lightweight framework to organize, access and execute your Python functions from the terminal.
Home-page: https://github.com/smetj/termfunk
Author: Jelle Smet
Author-email: development@smetj.net
License: UNKNOWN
Download-URL: https://github.com/smetj/termfunk/tarball/master
Platform: Linux
Classifier: Development Status :: 5 - Production/Stable
Classifier: License :: OSI Approved :: GNU General Public License v3 or later (GPLv3+)
Classifier: Programming Language :: Python
Classifier: Programming Language :: Python :: 3
Provides-Extra: testing
